{"retrieved_at": "2025-11-10T04:38:30.133585+00:00", "data": {"mal_id": 14623, "url": "https://myanimelist.net/anime/14623/Chikyuu_SOS_Sore_Ike_Kororin", "images": {"jpg": {"image_url": "https://cdn.myanimelist.net/images/anime/5/39807.jpg", "small_image_url": "https://cdn.myanimelist.net/images/anime/5/39807t.jpg", "large_image_url": "https://cdn.myanimelist.net/images/anime/5/39807l.jpg"}, "webp": {"image_url": "https://cdn.myanimelist.net/images/anime/5/39807.webp", "small_image_url": "https://cdn.myanimelist.net/images/anime/5/39807t.webp", "large_image_url": "https://cdn.myanimelist.net/images/anime/5/39807l.webp"}}, "trailer": {"youtube_id": null, "url": null, "embed_url": null, "images": {"image_url": null, "small_image_url": null, "medium_image_url": null, "large_image_url": null, "maximum_image_url": null}}, "approved": true, "titles": [{"type": "Default", "title": "Chikyuu SOS Sore Ike Kororin"}, {"type": "Japanese", "title": "地球SOSそれいけコロリン"}, {"type": "English", "title": "Do it Kororin Earth SOS"}], "title": "Chikyuu SOS Sore Ike Kororin", "title_english": "Do it Kororin Earth SOS", "title_japanese": "地球SOSそれいけコロリン", "title_synonyms": [], "type": "TV", "source": "Unknown", "episodes": 26, "status": "Finished Airing", "airing": false, "aired": {"from": "1992-04-08T00:00:00+00:00", "to": "1993-03-10T00:00:00+00:00", "prop": {"from": {"day": 8, "month": 4, "year": 1992}, "to": {"day": 10, "month": 3, "year": 1993}}, "string": "Apr 8, 1992 to Mar 10, 1993"}, "duration": "25 min per ep", "rating": "G - All Ages", "score": null, "scored_by": null, "rank": 20654, "popularity": 18650, "members": 441, "favorites": 1, "synopsis": "Jiang came to the old family cherry blossom viewing venue. But the surrounding area was full of garbage. He sits there to eat lunch reluctantly when a strange creature falls from the sky!\n\nKororin is his name. He comes from the Star Oasis and is here to teach the importance of environmental consciousness with his ESP.\n\nJiang, his sister, and Kororin must battle Syndrome, the evil alien plotting the destruction of the Earth. The attempted destruction is usually through some environmental issue such as tearing a hole in the ozone, or changing the weather, or overuse of electricity, etc.", "background": "", "season": "spring", "year": 1992, "broadcast": {"day": null, "time": null, "timezone": null, "string": "Unknown"}, "producers": [{"mal_id": 111, "type": "anime", "name": "NHK", "url": "https://myanimelist.net/anime/producer/111/NHK"}, {"mal_id": 198, "type": "anime", "name": "Gakken", "url": "https://myanimelist.net/anime/producer/198/Gakken"}], "licensors": [], "studios": [{"mal_id": 36, "type": "anime", "name": "Gallop", "url": "https://myanimelist.net/anime/producer/36/Gallop"}], "genres": [{"mal_id": 1, "type": "anime", "name": "Action", "url": "https://myanimelist.net/anime/genre/1/Action"}, {"mal_id": 4, "type": "anime", "name": "Comedy", "url": "https://myanimelist.net/anime/genre/4/Comedy"}, {"mal_id": 24, "type": "anime", "name": "Sci-Fi", "url": "https://myanimelist.net/anime/genre/24/Sci-Fi"}], "explicit_genres": [], "themes": [], "demographics": [{"mal_id": 15, "type": "anime", "name": "Kids", "url": "https://myanimelist.net/anime/genre/15/Kids"}], "relations": [], "theme": {"openings": [], "endings": []}, "external": [{"name": "AniDB", "url": "https://anidb.net/perl-bin/animedb.pl?show=anime&aid=7328"}, {"name": "ANN", "url": "https://www.animenewsnetwork.com/encyclopedia/anime.php?id=1258"}, {"name": "Wikipedia", "url": "http://ja.wikipedia.org/wiki/%E5%9C%B0%E7%90%83SOS_%E3%81%9D%E3%82%8C%E3%81%84%E3%81%91%E3%82%B3%E3%83%AD%E3%83%AA%E3%83%B3"}], "streaming": []}}