{"retrieved_at": "2025-11-09T22:53:50.598863+00:00", "data": {"mal_id": 1758, "url": "https://myanimelist.net/anime/1758/Di_Gi_Charat_Tsuyu_Specials", "images": {"jpg": {"image_url": "https://cdn.myanimelist.net/images/anime/1766/95896.jpg", "small_image_url": "https://cdn.myanimelist.net/images/anime/1766/95896t.jpg", "large_image_url": "https://cdn.myanimelist.net/images/anime/1766/95896l.jpg"}, "webp": {"image_url": "https://cdn.myanimelist.net/images/anime/1766/95896.webp", "small_image_url": "https://cdn.myanimelist.net/images/anime/1766/95896t.webp", "large_image_url": "https://cdn.myanimelist.net/images/anime/1766/95896l.webp"}}, "trailer": {"youtube_id": null, "url": null, "embed_url": null, "images": {"image_url": null, "small_image_url": null, "medium_image_url": null, "large_image_url": null, "maximum_image_url": null}}, "approved": true, "titles": [{"type": "Default", "title": "Di Gi Charat Tsuyu Specials"}, {"type": "Synonym", "title": "Di Gi Charat Other Specials"}, {"type": "Japanese", "title": "Di Gi Charat 梅雨スペシャル"}], "title": "Di Gi Charat Tsuyu Specials", "title_english": null, "title_japanese": "Di Gi Charat 梅雨スペシャル", "title_synonyms": ["Di Gi Charat Other Specials"], "type": "Special", "source": "Original", "episodes": 2, "status": "Finished Airing", "airing": false, "aired": {"from": "2001-06-01T00:00:00+00:00", "to": null, "prop": {"from": {"day": 1, "month": 6, "year": 2001}, "to": {"day": null, "month": null, "year": null}}, "string": "Jun 1, 2001"}, "duration": "13 min per ep", "rating": "G - All Ages", "score": 6.57, "scored_by": 1350, "rank": 6875, "popularity": 10813, "members": 3135, "favorites": 2, "synopsis": "Di Gi Charat (call her Dejiko for short) and Petit Charat (the cute little charat) come down to Earth, where they want to be idols, or something like that. Rabi~en~Rose (a random girl with bunny ears) decides they're in her way of becoming an idol herself. They all end up working at Gamers, where various otaku, children, and humanoid fingers walk in and act like morons.\n\nContains:\nGema no Sumika\nTsusode shiu Engekidan (ii ne!)\n\n(Source: AniDB)", "background": "", "season": null, "year": null, "broadcast": {"day": null, "time": null, "timezone": null, "string": null}, "producers": [{"mal_id": 3098, "type": "anime", "name": "Aquatone", "url": "https://myanimelist.net/anime/producer/3098/Aquatone"}], "licensors": [], "studios": [{"mal_id": 11, "type": "anime", "name": "Madhouse", "url": "https://myanimelist.net/anime/producer/11/Madhouse"}], "genres": [{"mal_id": 4, "type": "anime", "name": "Comedy", "url": "https://myanimelist.net/anime/genre/4/Comedy"}], "explicit_genres": [], "themes": [], "demographics": [], "relations": [{"relation": "Parent Story", "entry": [{"mal_id": 293, "type": "anime", "name": "Di Gi Charat", "url": "https://myanimelist.net/anime/293/Di_Gi_Charat"}]}], "theme": {"openings": [], "endings": []}, "external": [{"name": "AniDB", "url": "https://anidb.net/perl-bin/animedb.pl?show=anime&aid=553"}], "streaming": []}}