{"retrieved_at": "2025-11-10T04:58:03.443947+00:00", "data": {"mal_id": 19993, "url": "https://myanimelist.net/anime/19993/Kaminari_Boy_Pikkari★bee", "images": {"jpg": {"image_url": "https://cdn.myanimelist.net/images/anime/1373/135786.jpg", "small_image_url": "https://cdn.myanimelist.net/images/anime/1373/135786t.jpg", "large_image_url": "https://cdn.myanimelist.net/images/anime/1373/135786l.jpg"}, "webp": {"image_url": "https://cdn.myanimelist.net/images/anime/1373/135786.webp", "small_image_url": "https://cdn.myanimelist.net/images/anime/1373/135786t.webp", "large_image_url": "https://cdn.myanimelist.net/images/anime/1373/135786l.webp"}}, "trailer": {"youtube_id": null, "url": null, "embed_url": null, "images": {"image_url": null, "small_image_url": null, "medium_image_url": null, "large_image_url": null, "maximum_image_url": null}}, "approved": true, "titles": [{"type": "Default", "title": "Kaminari Boy Pikkari★bee"}, {"type": "Synonym", "title": "Pikkaribee"}, {"type": "Synonym", "title": "Boy of the Thunders"}, {"type": "Japanese", "title": "かみなり坊やピッカリ★ビー"}], "title": "Kaminari Boy Pikkari★bee", "title_english": null, "title_japanese": "かみなり坊やピッカリ★ビー", "title_synonyms": ["Pikkaribee", "Boy of the Thunders"], "type": "TV", "source": "Unknown", "episodes": 53, "status": "Finished Airing", "airing": false, "aired": {"from": "1967-04-01T00:00:00+00:00", "to": "1968-03-30T00:00:00+00:00", "prop": {"from": {"day": 1, "month": 4, "year": 1967}, "to": {"day": 30, "month": 3, "year": 1968}}, "string": "Apr 1, 1967 to Mar 30, 1968"}, "duration": "25 min per ep", "rating": "PG - Children", "score": null, "scored_by": null, "rank": 17680, "popularity": 16346, "members": 684, "favorites": 1, "synopsis": "A comedy about a mischievous boy. Each episode contains 2 stories.\n\nBased on a manga by Murotani Tsunezou.\n\n(Source: AniDB)", "background": "", "season": "spring", "year": 1967, "broadcast": {"day": null, "time": null, "timezone": null, "string": "Unknown"}, "producers": [{"mal_id": 143, "type": "anime", "name": "Mainichi Broadcasting System", "url": "https://myanimelist.net/anime/producer/143/Mainichi_Broadcasting_System"}], "licensors": [], "studios": [{"mal_id": 991, "type": "anime", "name": "Hoso Seisaku Doga", "url": "https://myanimelist.net/anime/producer/991/Hoso_Seisaku_Doga"}, {"mal_id": 3158, "type": "anime", "name": "Children's Corner", "url": "https://myanimelist.net/anime/producer/3158/Childrens_Corner"}], "genres": [{"mal_id": 2, "type": "anime", "name": "Adventure", "url": "https://myanimelist.net/anime/genre/2/Adventure"}, {"mal_id": 4, "type": "anime", "name": "Comedy", "url": "https://myanimelist.net/anime/genre/4/Comedy"}], "explicit_genres": [], "themes": [], "demographics": [{"mal_id": 15, "type": "anime", "name": "Kids", "url": "https://myanimelist.net/anime/genre/15/Kids"}], "relations": [{"relation": "Character", "entry": [{"mal_id": 39501, "type": "anime", "name": "Kaminari Boy Pikatta-kun no Koutsuu Anzen", "url": "https://myanimelist.net/anime/39501/Kaminari_Boy_Pikatta-kun_no_Koutsuu_Anzen"}, {"mal_id": 39502, "type": "anime", "name": "Kaminari Boy Pikatta-kun no Jitensha Kyoushitsu", "url": "https://myanimelist.net/anime/39502/Kaminari_Boy_Pikatta-kun_no_Jitensha_Kyoushitsu"}]}], "theme": {"openings": ["\"Pikaribee no Uta (ピッカリ・ビーのうた)\" by Fusako Amachi, Bon Cool"], "endings": ["\"Kumo no Doraibu (雲のドライブ)\" by Miho Kururi"]}, "external": [{"name": "AniDB", "url": "https://anidb.net/perl-bin/animedb.pl?show=anime&aid=5090"}, {"name": "ANN", "url": "https://www.animenewsnetwork.com/encyclopedia/anime.php?id=182"}, {"name": "Wikipedia", "url": "http://ja.wikipedia.org/wiki/%E3%81%8B%E3%81%BF%E3%81%AA%E3%82%8A%E5%9D%8A%E3%82%84%E3%83%94%E3%83%83%E3%82%AB%E3%83%AA%E3%83%BB%E3%83%93%E3%83%BC"}], "streaming": []}}