{"retrieved_at": "2025-11-10T05:03:31.514861+00:00", "data": {"mal_id": 21547, "url": "https://myanimelist.net/anime/21547/Shin_Choubakumatsu_Shounen_Seiki_Takamaru", "images": {"jpg": {"image_url": "https://cdn.myanimelist.net/images/anime/11/56783.jpg", "small_image_url": "https://cdn.myanimelist.net/images/anime/11/56783t.jpg", "large_image_url": "https://cdn.myanimelist.net/images/anime/11/56783l.jpg"}, "webp": {"image_url": "https://cdn.myanimelist.net/images/anime/11/56783.webp", "small_image_url": "https://cdn.myanimelist.net/images/anime/11/56783t.webp", "large_image_url": "https://cdn.myanimelist.net/images/anime/11/56783l.webp"}}, "trailer": {"youtube_id": null, "url": null, "embed_url": null, "images": {"image_url": null, "small_image_url": null, "medium_image_url": null, "large_image_url": null, "maximum_image_url": null}}, "approved": true, "titles": [{"type": "Default", "title": "Shin Choubakumatsu Shounen Seiki Takamaru"}, {"type": "Synonym", "title": "Shin Cho Bakumatsu Shonen Seiki Takamaru"}, {"type": "Synonym", "title": "Children Build The Future"}, {"type": "Japanese", "title": "新・超幕末少年世紀タカマル"}], "title": "Shin Choubakumatsu Shounen Seiki Takamaru", "title_english": null, "title_japanese": "新・超幕末少年世紀タカマル", "title_synonyms": ["Shin Cho Bakumatsu Shonen Seiki Takamaru", "Children Build The Future"], "type": "OVA", "source": "Unknown", "episodes": 6, "status": "Finished Airing", "airing": false, "aired": {"from": "1992-11-21T00:00:00+00:00", "to": "1993-06-20T00:00:00+00:00", "prop": {"from": {"day": 21, "month": 11, "year": 1992}, "to": {"day": 20, "month": 6, "year": 1993}}, "string": "Nov 21, 1992 to Jun 20, 1993"}, "duration": "28 min per ep", "rating": "PG-13 - Teens 13 or older", "score": null, "scored_by": null, "rank": 15011, "popularity": 18184, "members": 476, "favorites": 0, "synopsis": null, "background": "", "season": null, "year": null, "broadcast": {"day": null, "time": null, "timezone": null, "string": null}, "producers": [], "licensors": [], "studios": [{"mal_id": 7, "type": "anime", "name": "J.C.Staff", "url": "https://myanimelist.net/anime/producer/7/JCStaff"}], "genres": [{"mal_id": 1, "type": "anime", "name": "Action", "url": "https://myanimelist.net/anime/genre/1/Action"}, {"mal_id": 4, "type": "anime", "name": "Comedy", "url": "https://myanimelist.net/anime/genre/4/Comedy"}, {"mal_id": 10, "type": "anime", "name": "Fantasy", "url": "https://myanimelist.net/anime/genre/10/Fantasy"}], "explicit_genres": [], "themes": [], "demographics": [], "relations": [{"relation": "Prequel", "entry": [{"mal_id": 21545, "type": "anime", "name": "Choubakumatsu Shounen Seiki Takamaru", "url": "https://myanimelist.net/anime/21545/Choubakumatsu_Shounen_Seiki_Takamaru"}]}], "theme": {"openings": ["\"Neppuu Shounen Roku: Come on Chanpon Tengoku (熱風少年録 -Come on ちゃんぽん天国)\" by Kasahara Hiroko and Chanpon Five (ちゃんぽんファイブ)"], "endings": []}, "external": [{"name": "AniDB", "url": "https://anidb.net/perl-bin/animedb.pl?show=anime&aid=3371"}, {"name": "ANN", "url": "https://www.animenewsnetwork.com/encyclopedia/anime.php?id=7265"}], "streaming": []}}