{"retrieved_at": "2025-11-10T05:13:49.592105+00:00", "data": {"mal_id": 23855, "url": "https://myanimelist.net/anime/23855/Dennou_Sentai_Voogies★Angel_Gaiden__Susume_Super★Angels", "images": {"jpg": {"image_url": "https://cdn.myanimelist.net/images/anime/2/61707.jpg", "small_image_url": "https://cdn.myanimelist.net/images/anime/2/61707t.jpg", "large_image_url": "https://cdn.myanimelist.net/images/anime/2/61707l.jpg"}, "webp": {"image_url": "https://cdn.myanimelist.net/images/anime/2/61707.webp", "small_image_url": "https://cdn.myanimelist.net/images/anime/2/61707t.webp", "large_image_url": "https://cdn.myanimelist.net/images/anime/2/61707l.webp"}}, "trailer": {"youtube_id": null, "url": null, "embed_url": null, "images": {"image_url": null, "small_image_url": null, "medium_image_url": null, "large_image_url": null, "maximum_image_url": null}}, "approved": true, "titles": [{"type": "Default", "title": "Dennou Sentai Voogie's★Angel Gaiden: Susume! Super★Angels!"}, {"type": "Synonym", "title": "Voogie's Angel OVA"}, {"type": "Synonym", "title": "Susume! Super Angels!"}, {"type": "Synonym", "title": "Dash! Super Angels!"}, {"type": "Japanese", "title": "電脳戦隊ヴギィ'ズ★エンジェル外伝 進め! スーパー★エンジェルス!"}], "title": "Dennou Sentai Voogie's★Angel Gaiden: Susume! Super★Angels!", "title_english": null, "title_japanese": "電脳戦隊ヴギィ'ズ★エンジェル外伝 進め! スーパー★エンジェルス!", "title_synonyms": ["Voogie's Angel OVA", "Susume! Super Angels!", "Dash! Super Angels!"], "type": "OVA", "source": "Unknown", "episodes": 2, "status": "Finished Airing", "airing": false, "aired": {"from": "1998-08-21T00:00:00+00:00", "to": "1998-09-19T00:00:00+00:00", "prop": {"from": {"day": 21, "month": 8, "year": 1998}, "to": {"day": 19, "month": 9, "year": 1998}}, "string": "Aug 21, 1998 to Sep 19, 1998"}, "duration": "16 min per ep", "rating": "PG-13 - Teens 13 or older", "score": 5.61, "scored_by": 142, "rank": 12202, "popularity": 15208, "members": 908, "favorites": 1, "synopsis": "SD parody version of Voogie's Angel based on its radio drama of the same name.", "background": "", "season": null, "year": null, "broadcast": {"day": null, "time": null, "timezone": null, "string": null}, "producers": [], "licensors": [], "studios": [{"mal_id": 7, "type": "anime", "name": "J.C.Staff", "url": "https://myanimelist.net/anime/producer/7/JCStaff"}], "genres": [{"mal_id": 4, "type": "anime", "name": "Comedy", "url": "https://myanimelist.net/anime/genre/4/Comedy"}, {"mal_id": 24, "type": "anime", "name": "Sci-Fi", "url": "https://myanimelist.net/anime/genre/24/Sci-Fi"}], "explicit_genres": [], "themes": [{"mal_id": 18, "type": "anime", "name": "Mecha", "url": "https://myanimelist.net/anime/genre/18/Mecha"}, {"mal_id": 20, "type": "anime", "name": "Parody", "url": "https://myanimelist.net/anime/genre/20/Parody"}], "demographics": [], "relations": [{"relation": "Parent Story", "entry": [{"mal_id": 2453, "type": "anime", "name": "Dennou Sentai Voogie's★Angel", "url": "https://myanimelist.net/anime/2453/Dennou_Sentai_Voogies★Angel"}]}], "theme": {"openings": [], "endings": []}, "external": [{"name": "AniDB", "url": "https://anidb.net/perl-bin/animedb.pl?show=anime&aid=7201"}, {"name": "Wikipedia", "url": "http://ja.wikipedia.org/wiki/%E9%9B%BB%E8%84%B3%E6%88%A6%E9%9A%8A%E3%83%B4%E3%82%AE%E3%82%A3'%E3%82%BA%E2%98%85%E3%82%A8%E3%83%B3%E3%82%B8%E3%82%A7%E3%83%AB#.E3.83.93.E3.83.87.E3.82.AA"}], "streaming": []}}