{"retrieved_at": "2025-11-10T03:08:06.819125+00:00", "data": {"mal_id": 2423, "url": "https://myanimelist.net/anime/2423/Grey__Digital_Target", "images": {"jpg": {"image_url": "https://cdn.myanimelist.net/images/anime/1301/94928.jpg", "small_image_url": "https://cdn.myanimelist.net/images/anime/1301/94928t.jpg", "large_image_url": "https://cdn.myanimelist.net/images/anime/1301/94928l.jpg"}, "webp": {"image_url": "https://cdn.myanimelist.net/images/anime/1301/94928.webp", "small_image_url": "https://cdn.myanimelist.net/images/anime/1301/94928t.webp", "large_image_url": "https://cdn.myanimelist.net/images/anime/1301/94928l.webp"}}, "trailer": {"youtube_id": null, "url": null, "embed_url": null, "images": {"image_url": null, "small_image_url": null, "medium_image_url": null, "large_image_url": null, "maximum_image_url": null}}, "approved": true, "titles": [{"type": "Default", "title": "Grey: Digital Target"}, {"type": "Japanese", "title": "GREY デジタル・ターゲット"}, {"type": "French", "title": "Grey: Cible Digitale"}], "title": "Grey: Digital Target", "title_english": null, "title_japanese": "GREY デジタル・ターゲット", "title_synonyms": [], "type": "Movie", "source": "Manga", "episodes": 1, "status": "Finished Airing", "airing": false, "aired": {"from": "1986-12-13T00:00:00+00:00", "to": null, "prop": {"from": {"day": 13, "month": 12, "year": 1986}, "to": {"day": null, "month": null, "year": null}}, "string": "Dec 13, 1986"}, "duration": "1 hr 13 min", "rating": "R+ - Mild Nudity", "score": 6, "scored_by": 1350, "rank": 10254, "popularity": 10451, "members": 3472, "favorites": 4, "synopsis": "Grey is a laconic trooper in a rough, futuristic military system which rewards success in battle with high pay and promotions, but only three precent of troopers live long enough for the final goal - citizenship and the chance for a life above the misery of most of the populace. Grey has managed to keep coming back alive, even earning the nickname Grey Death. But is the society he's fought for worth it?\n\n(Source: ANN)", "background": "", "season": null, "year": null, "broadcast": {"day": null, "time": null, "timezone": null, "string": null}, "producers": [{"mal_id": 905, "type": "anime", "name": "Tokuma Japan", "url": "https://myanimelist.net/anime/producer/905/Tokuma_Japan"}], "licensors": [{"mal_id": 119, "type": "anime", "name": "VIZ Media", "url": "https://myanimelist.net/anime/producer/119/VIZ_Media"}], "studios": [{"mal_id": 207, "type": "anime", "name": "Magic Bus", "url": "https://myanimelist.net/anime/producer/207/Magic_Bus"}], "genres": [{"mal_id": 1, "type": "anime", "name": "Action", "url": "https://myanimelist.net/anime/genre/1/Action"}, {"mal_id": 8, "type": "anime", "name": "Drama", "url": "https://myanimelist.net/anime/genre/8/Drama"}, {"mal_id": 24, "type": "anime", "name": "Sci-Fi", "url": "https://myanimelist.net/anime/genre/24/Sci-Fi"}], "explicit_genres": [], "themes": [{"mal_id": 38, "type": "anime", "name": "Military", "url": "https://myanimelist.net/anime/genre/38/Military"}], "demographics": [{"mal_id": 27, "type": "anime", "name": "Shounen", "url": "https://myanimelist.net/anime/genre/27/Shounen"}], "relations": [{"relation": "Adaptation", "entry": [{"mal_id": 2701, "type": "manga", "name": "Grey", "url": "https://myanimelist.net/manga/2701/Grey"}]}], "theme": {"openings": [], "endings": ["\"Love is Heart: Seiza no Kodomo-tachi (LOVE IS HEART -星座の子供たち-)\" by Yuuri Sugimoto"]}, "external": [{"name": "Official Site", "url": "http://ashipro.jp/works/theatrical/w007.html"}, {"name": "AniDB", "url": "https://anidb.net/perl-bin/animedb.pl?show=anime&aid=1515"}, {"name": "ANN", "url": "https://www.animenewsnetwork.com/encyclopedia/anime.php?id=673"}, {"name": "Wikipedia", "url": "http://en.wikipedia.org/wiki/Grey_(manga)"}], "streaming": []}}