{"retrieved_at": "2025-11-10T05:40:21.125598+00:00", "data": {"mal_id": 30267, "url": "https://myanimelist.net/anime/30267/Chan_Shuo_A_Kuan", "images": {"jpg": {"image_url": "https://cdn.myanimelist.net/images/anime/10/72440.jpg", "small_image_url": "https://cdn.myanimelist.net/images/anime/10/72440t.jpg", "large_image_url": "https://cdn.myanimelist.net/images/anime/10/72440l.jpg"}, "webp": {"image_url": "https://cdn.myanimelist.net/images/anime/10/72440.webp", "small_image_url": "https://cdn.myanimelist.net/images/anime/10/72440t.webp", "large_image_url": "https://cdn.myanimelist.net/images/anime/10/72440l.webp"}}, "trailer": {"youtube_id": null, "url": null, "embed_url": null, "images": {"image_url": null, "small_image_url": null, "medium_image_url": null, "large_image_url": null, "maximum_image_url": null}}, "approved": true, "titles": [{"type": "Default", "title": "Chan Shuo A Kuan"}, {"type": "Japanese", "title": "禅说阿宽"}], "title": "Chan Shuo A Kuan", "title_english": null, "title_japanese": "禅说阿宽", "title_synonyms": [], "type": "Movie", "source": "Unknown", "episodes": 1, "status": "Finished Airing", "airing": false, "aired": {"from": "1994-01-01T00:00:00+00:00", "to": null, "prop": {"from": {"day": 1, "month": 1, "year": 1994}, "to": {"day": null, "month": null, "year": null}}, "string": "1994"}, "duration": "1 hr 33 min", "rating": null, "score": null, "scored_by": null, "rank": 20530, "popularity": 22222, "members": 219, "favorites": 0, "synopsis": null, "background": "", "season": null, "year": null, "broadcast": {"day": null, "time": null, "timezone": null, "string": null}, "producers": [], "licensors": [], "studios": [], "genres": [{"mal_id": 4, "type": "anime", "name": "Comedy", "url": "https://myanimelist.net/anime/genre/4/Comedy"}, {"mal_id": 36, "type": "anime", "name": "Slice of Life", "url": "https://myanimelist.net/anime/genre/36/Slice_of_Life"}], "explicit_genres": [], "themes": [], "demographics": [], "relations": [], "theme": {"openings": [], "endings": []}, "external": [], "streaming": []}}