{"retrieved_at": "2025-11-10T04:06:09.738229+00:00", "data": {"mal_id": 8471, "url": "https://myanimelist.net/anime/8471/Naoko_no_Tropic_Angel__Hyouryuu", "images": {"jpg": {"image_url": "https://cdn.myanimelist.net/images/anime/7/57365.jpg", "small_image_url": "https://cdn.myanimelist.net/images/anime/7/57365t.jpg", "large_image_url": "https://cdn.myanimelist.net/images/anime/7/57365l.jpg"}, "webp": {"image_url": "https://cdn.myanimelist.net/images/anime/7/57365.webp", "small_image_url": "https://cdn.myanimelist.net/images/anime/7/57365t.webp", "large_image_url": "https://cdn.myanimelist.net/images/anime/7/57365l.webp"}}, "trailer": {"youtube_id": null, "url": null, "embed_url": null, "images": {"image_url": null, "small_image_url": null, "medium_image_url": null, "large_image_url": null, "maximum_image_url": null}}, "approved": true, "titles": [{"type": "Default", "title": "Naoko no Tropic Angel: Hyouryuu"}, {"type": "Synonym", "title": "Naoko no Tropic Angel Hyoryu"}, {"type": "Japanese", "title": "直子のトロピックエンジェル 〜漂流〜"}], "title": "Naoko no Tropic Angel: Hyouryuu", "title_english": null, "title_japanese": "直子のトロピックエンジェル 〜漂流〜", "title_synonyms": ["Naoko no Tropic Angel Hyoryu"], "type": "OVA", "source": "Unknown", "episodes": 1, "status": "Finished Airing", "airing": false, "aired": {"from": "1985-05-10T00:00:00+00:00", "to": null, "prop": {"from": {"day": 10, "month": 5, "year": 1985}, "to": {"day": null, "month": null, "year": null}}, "string": "May 10, 1985"}, "duration": "22 min", "rating": "Rx - Hentai", "score": 5.22, "scored_by": 340, "rank": null, "popularity": 14617, "members": 1065, "favorites": 1, "synopsis": "One of the first adult OVA. Released in 1985. The Naoko in the title refers to the original author, not a character. \n\n(Source: AniDB)", "background": "", "season": null, "year": null, "broadcast": {"day": null, "time": null, "timezone": null, "string": null}, "producers": [], "licensors": [], "studios": [], "genres": [{"mal_id": 12, "type": "anime", "name": "Hentai", "url": "https://myanimelist.net/anime/genre/12/Hentai"}], "explicit_genres": [], "themes": [], "demographics": [], "relations": [], "theme": {"openings": [], "endings": []}, "external": [{"name": "AniDB", "url": "https://anidb.net/perl-bin/animedb.pl?show=anime&aid=6425"}], "streaming": []}}